rawgql.py
rawgql-0.1.dev1.dist-info/LICENSE
rawgql-0.1.dev1.dist-info/METADATA
rawgql-0.1.dev1.dist-info/WHEEL
rawgql-0.1.dev1.dist-info/top_level.txt
rawgql-0.1.dev1.dist-info/RECORD
