Metadata-Version: 2.1
Name: rawgql
Version: 0.1.dev1
Summary: Simple Python 3 framework for interacting with GraphQL endpoints
Home-page: https://github.com/jamwil/rawgql
Author: James Williams
Author-email: jamwil@gmail.com
License: MIT
Keywords: graphql
Platform: UNKNOWN
Classifier: Programming Language :: Python :: 3
Classifier: License :: OSI Approved :: MIT License
Classifier: Operating System :: OS Independent
Classifier: Development Status :: 3 - Alpha
Classifier: Natural Language :: English
Classifier: Topic :: Database
Requires-Dist: requests
